webraft/__init__.py
webraft/core.py
webraft/engine.py
webraft/generator.py
webraft/ipinfo.py
webraft/process.py
webraft/validate.py
webraft-0.6.dist-info/METADATA
webraft-0.6.dist-info/WHEEL
webraft-0.6.dist-info/top_level.txt
webraft-0.6.dist-info/RECORD
